S1Tiling-0.2.0rc6.data/scripts/S1Processor.py
s1tiling/S1Processor.py
s1tiling/__init__.py
s1tiling/__meta__.py
s1tiling/ewoc_s1_processor.py
s1tiling/logging.conf.yaml
s1tiling/s1tiling-cluster.py
s1tiling/libs/S1DateAcquisition.py
s1tiling/libs/S1FileManager.py
s1tiling/libs/S1FilteringProcessor.py
s1tiling/libs/Utils.py
s1tiling/libs/__init__.py
s1tiling/libs/configuration.py
s1tiling/libs/exits.py
s1tiling/libs/otbpipeline.py
s1tiling/libs/otbwrappers.py
s1tiling/libs/vis.py
s1tiling/resources/Geoid/egm96.grd
s1tiling/resources/Geoid/egm96.grd.hdr
s1tiling/resources/shapefile/Features.dbf
s1tiling/resources/shapefile/Features.prj
s1tiling/resources/shapefile/Features.shp
s1tiling/resources/shapefile/Features.shx
s1tiling/resources/shapefile/Info.dbf
s1tiling/resources/shapefile/Info.prj
s1tiling/resources/shapefile/Info.shp
s1tiling/resources/shapefile/Info.shx
s1tiling/resources/shapefile/srtm.dbf
s1tiling/resources/shapefile/srtm.prj
s1tiling/resources/shapefile/srtm.shp
s1tiling/resources/shapefile/srtm.shx
s1tiling/resources/shapefile/srtm_tiles.gpkg
S1Tiling-0.2.0rc6.dist-info/LICENSE
S1Tiling-0.2.0rc6.dist-info/METADATA
S1Tiling-0.2.0rc6.dist-info/WHEEL
S1Tiling-0.2.0rc6.dist-info/entry_points.txt
S1Tiling-0.2.0rc6.dist-info/top_level.txt
S1Tiling-0.2.0rc6.dist-info/RECORD
