Metadata-Version: 2.1
Name: S1Tiling
Version: 0.2.0rc6
Summary: On demand Ortho-rectification of Sentinel-1 data on Sentinel-2 grid.
Home-page: https://gitlab.orfeo-toolbox.org/s1-tiling/s1tiling
Author: Thierry KOLECK
Author-email: Thierry.Koleck@cnes.fr
License: Apache 2.0
Project-URL: Bug Tracker, https://gitlab.orfeo-toolbox.org/s1-tiling/s1tiling/-/issues
Project-URL: Documentation, https://s1-tiling.pages.orfeo-toolbox.org/s1tiling/latest
Project-URL: Source Code, https://gitlab.orfeo-toolbox.org/s1-tiling/s1tiling
Keywords: Sentinel-1,Sentinel-2,orthorectification
Platform: UNKNOWN
Classifier: Development Status :: 4 - Beta
Classifier: Environment :: Console
Classifier: Intended Audience :: Developers
Classifier: Intended Audience :: Science/Research
Classifier: License :: OSI Approved :: Apache Software License
Classifier: Natural Language :: English
Classifier: Operating System :: OS Independent
Classifier: Programming Language :: Python
Classifier: Programming Language :: Python :: 3.3
Classifier: Programming Language :: Python :: 3.4
Classifier: Programming Language :: Python :: 3.5
Classifier: Programming Language :: Python :: 3.6
Classifier: Programming Language :: Python :: 3.7
Classifier: Programming Language :: Python :: 3.8
Classifier: Topic :: Scientific/Engineering :: GIS
Requires-Python: >=3.3, <4
Requires-Dist: click
Requires-Dist: dask[distributed]
Requires-Dist: eodag
Requires-Dist: gdal (==3.2.2)
Requires-Dist: graphviz
Requires-Dist: numpy
Requires-Dist: objgraph
Requires-Dist: pympler
Requires-Dist: pyyaml
Provides-Extra: dev
Requires-Dist: wheel ; extra == 'dev'
Requires-Dist: flake8 ; extra == 'dev'
Requires-Dist: pre-commit ; extra == 'dev'
Requires-Dist: pytest-check ; extra == 'dev'
Requires-Dist: pytest-icdiff ; extra == 'dev'
Requires-Dist: pylint ; extra == 'dev'
Provides-Extra: docs
Requires-Dist: sphinx (==1.8.0) ; extra == 'docs'
Requires-Dist: natsort ; extra == 'docs'
Requires-Dist: nbsphinx (==0.3.5) ; extra == 'docs'
Requires-Dist: nbsphinx-link (==1.1.1) ; extra == 'docs'
Requires-Dist: m2r2 ; extra == 'docs'
Requires-Dist: sphinx-rtd-theme ; extra == 'docs'
